README.md
setup.py
starlette_oauth2_api.py
starlette_oauth2_api.egg-info/PKG-INFO
starlette_oauth2_api.egg-info/SOURCES.txt
starlette_oauth2_api.egg-info/dependency_links.txt
starlette_oauth2_api.egg-info/requires.txt
starlette_oauth2_api.egg-info/top_level.txt