Metadata-Version: 2.1
Name: starlette-oauth2-api
Version: 0.2.4
Summary: UNKNOWN
Home-page: https://gitlab.com/jorgecarleitao/starlette-oauth2-api
Author: Jorge C. Leitao
Author-email: jorgecarleitao@gmail.com
License: UNKNOWN
Platform: UNKNOWN
